{"cameraMode":{"drawMode":0,"name":"Shaded","section":"Shading Mode"},"sceneLighting":false,"audioPlay":false,"sceneViewState":{"m_AlwaysRefresh":false,"showFog":true,"showSkybox":true,"showFlares":true,"showImageEffects":true,"showParticleSystems":true,"showVisualEffectGraphs":true,"m_FxEnabled":true},"in2DMode":false,"pivot":{"x":-12.67377758026123,"y":3.8146843910217287,"z":-114.2618179321289},"rotation":{"x":0.10448293387889862,"y":-0.5332083106040955,"z":0.06549514830112457,"w":0.8372999429702759},"size":1.2247449159622193,"orthographic":false}